{
    "database_name": "Title",
    "server": "10.88.88.200",
    "export_date": "2026-02-17T15:43:33.693126",
    "total_tables": 2,
    "schema": {
        "dbo.Title": {
            "schema": "dbo",
            "table_name": "Title",
            "columns": [
                {
                    "column_name": "Title_ID",
                    "data_type": "int",
                    "ordinal_position": 1,
                    "is_nullable": "NO",
                    "column_default": null,
                    "precision": 10,
                    "scale": 0
                },
                {
                    "column_name": "Title_Name",
                    "data_type": "nvarchar",
                    "ordinal_position": 2,
                    "is_nullable": "NO",
                    "column_default": null,
                    "max_length": 512
                },
                {
                    "column_name": "Detail",
                    "data_type": "nvarchar",
                    "ordinal_position": 3,
                    "is_nullable": "YES",
                    "column_default": null,
                    "max_length": 1024
                },
                {
                    "column_name": "Is_Active",
                    "data_type": "int",
                    "ordinal_position": 4,
                    "is_nullable": "NO",
                    "column_default": null,
                    "precision": 10,
                    "scale": 0
                },
                {
                    "column_name": "Is_Deleted",
                    "data_type": "int",
                    "ordinal_position": 5,
                    "is_nullable": "NO",
                    "column_default": null,
                    "precision": 10,
                    "scale": 0
                },
                {
                    "column_name": "Created_By",
                    "data_type": "int",
                    "ordinal_position": 6,
                    "is_nullable": "NO",
                    "column_default": null,
                    "precision": 10,
                    "scale": 0
                },
                {
                    "column_name": "Updated_By",
                    "data_type": "int",
                    "ordinal_position": 7,
                    "is_nullable": "YES",
                    "column_default": null,
                    "precision": 10,
                    "scale": 0
                },
                {
                    "column_name": "Created_Date",
                    "data_type": "smalldatetime",
                    "ordinal_position": 8,
                    "is_nullable": "NO",
                    "column_default": null
                },
                {
                    "column_name": "Updated_Date",
                    "data_type": "smalldatetime",
                    "ordinal_position": 9,
                    "is_nullable": "YES",
                    "column_default": null
                }
            ]
        },
        "dbo.Title_Translate": {
            "schema": "dbo",
            "table_name": "Title_Translate",
            "columns": [
                {
                    "column_name": "Translate_ID",
                    "data_type": "int",
                    "ordinal_position": 1,
                    "is_nullable": "NO",
                    "column_default": null,
                    "precision": 10,
                    "scale": 0
                },
                {
                    "column_name": "Language_ID",
                    "data_type": "int",
                    "ordinal_position": 2,
                    "is_nullable": "NO",
                    "column_default": null,
                    "precision": 10,
                    "scale": 0
                },
                {
                    "column_name": "Title_ID",
                    "data_type": "int",
                    "ordinal_position": 3,
                    "is_nullable": "NO",
                    "column_default": null,
                    "precision": 10,
                    "scale": 0
                },
                {
                    "column_name": "Original",
                    "data_type": "nvarchar",
                    "ordinal_position": 4,
                    "is_nullable": "NO",
                    "column_default": null,
                    "max_length": -1
                },
                {
                    "column_name": "Translate",
                    "data_type": "nvarchar",
                    "ordinal_position": 5,
                    "is_nullable": "NO",
                    "column_default": null,
                    "max_length": -1
                },
                {
                    "column_name": "Field_Name",
                    "data_type": "nvarchar",
                    "ordinal_position": 6,
                    "is_nullable": "YES",
                    "column_default": null,
                    "max_length": 256
                },
                {
                    "column_name": "Created_By",
                    "data_type": "int",
                    "ordinal_position": 7,
                    "is_nullable": "NO",
                    "column_default": null,
                    "precision": 10,
                    "scale": 0
                },
                {
                    "column_name": "Created_Date",
                    "data_type": "datetime",
                    "ordinal_position": 8,
                    "is_nullable": "NO",
                    "column_default": null
                },
                {
                    "column_name": "Updated_By",
                    "data_type": "int",
                    "ordinal_position": 9,
                    "is_nullable": "YES",
                    "column_default": null,
                    "precision": 10,
                    "scale": 0
                },
                {
                    "column_name": "Updated_Date",
                    "data_type": "datetime",
                    "ordinal_position": 10,
                    "is_nullable": "YES",
                    "column_default": "(getdate())"
                }
            ]
        }
    }
}